ezencode/EZencode.py
ezencode/__init__.py
ezencode/__main__.py
ezencode/decoder.py
ezencode/encoder.py
ezencode/maps.py
ezencode-0.8.dist-info/METADATA
ezencode-0.8.dist-info/WHEEL
ezencode-0.8.dist-info/entry_points.txt
ezencode-0.8.dist-info/licenses/LICENSE
ezencode-0.8.dist-info/RECORD
