Metadata-Version: 2.4
Name: ezencode
Version: 0.8
Summary: A simple text encoder: EZ Encode
Author-email: "Rayshawn Levy (sneekyfoxx)" <sneekyfoxx09@gmail.com>
Maintainer-email: "Rayshawn Levy (sneekyfoxx)" <sneekyfoxx09@gmail.com>
License-Expression: BSD-3-Clause
License-File: LICENSE
Keywords: EZ,decode,encode,ez,ezencode
Classifier: Development Status :: 5 - Production/Stable
Classifier: Operating System :: OS Independent
Classifier: Programming Language :: Python :: 3.12
Classifier: Programming Language :: Python :: 3.13
Requires-Python: >=3.13
